etspy/__init__.py
etspy/align.py
etspy/api.py
etspy/base.py
etspy/datasets.py
etspy/hyperspy_extension.yaml
etspy/io.py
etspy/recon.py
etspy/simulation.py
etspy/tests/.coveragerc-cuda
etspy/tests/.coveragerc-nocuda
etspy/tests/__init__.py
etspy/tests/test_align.py
etspy/tests/test_base.py
etspy/tests/test_cuda.py
etspy/tests/test_data/Catalyst3DModel_TiltSeries180.hdf5
etspy/tests/test_data/DM_Series_Test/BF_001.dm3
etspy/tests/test_data/DM_Series_Test/BF_002.dm3
etspy/tests/test_data/DM_Series_Test/BF_003.dm3
etspy/tests/test_data/HAADF.ali
etspy/tests/test_data/HAADF.dm3
etspy/tests/test_data/HAADF.mrc
etspy/tests/test_data/HAADF.rawtlt
etspy/tests/test_data/HAADF.txt
etspy/tests/test_data/HAADF_Aligned.hdf5
etspy/tests/test_data/SerialEM_MultiTilt_Test/test_000.mdoc
etspy/tests/test_data/SerialEM_MultiTilt_Test/test_000.mrc
etspy/tests/test_data/SerialEM_Multiframe_Test/test_000.mdoc
etspy/tests/test_data/SerialEM_Multiframe_Test/test_000.mrc
etspy/tests/test_data/SerialEM_Multiframe_Test/test_000.mrc.mdoc
etspy/tests/test_data/SerialEM_Multiframe_Test/test_001.mdoc
etspy/tests/test_data/SerialEM_Multiframe_Test/test_001.mrc
etspy/tests/test_data/SerialEM_Multiframe_Test/test_001.mrc.mdoc
etspy/tests/test_data/SerialEM_Multiframe_Test/test_002.mdoc
etspy/tests/test_data/SerialEM_Multiframe_Test/test_002.mrc
etspy/tests/test_data/SerialEM_Multiframe_Test/test_002.mrc.mdoc
etspy/tests/test_datasets.py
etspy/tests/test_io.py
etspy/tests/test_recon.py
etspy/tests/test_simulation.py
etspy/tests/test_utils.py
etspy/tests/test_version.py
etspy/utils.py
etspy-1.0.1.dist-info/LICENSE
etspy-1.0.1.dist-info/METADATA
etspy-1.0.1.dist-info/WHEEL
etspy-1.0.1.dist-info/entry_points.txt
etspy-1.0.1.dist-info/RECORD
