Metadata-Version: 2.1
Name: etspy
Version: 1.0.1
Summary: Suite of tools for processing and reconstruction of electron tomography data
Home-page: https://pages.nist.gov/etspy/
License: NIST Public License
Author: Andrew A. Herzing
Author-email: andrew.herzing@nist.gov
Requires-Python: >=3.10,<3.13
Classifier: License :: Other/Proprietary License
Classifier: Programming Language :: Python :: 3
Classifier: Programming Language :: Python :: 3.10
Classifier: Programming Language :: Python :: 3.11
Classifier: Programming Language :: Python :: 3.12
Provides-Extra: all
Provides-Extra: gpu
Provides-Extra: jupyter
Requires-Dist: astra-toolbox (>=2.1)
Requires-Dist: cupy (>=13.3.0,<14.0.0) ; extra == "gpu" or extra == "all"
Requires-Dist: h5py (>=3.12.1,<4.0.0)
Requires-Dist: hyperspy (>=2.1.1,<3.0.0)
Requires-Dist: hyperspy-gui-ipywidgets (>=2.0.2,<3.0.0)
Requires-Dist: ipykernel (>=6.29.5,<7.0.0) ; extra == "jupyter" or extra == "all"
Requires-Dist: numba (>=0.60.0,<0.61.0)
Requires-Dist: numpy (>1.26)
Requires-Dist: pystackreg (>=0.2.8,<0.3.0)
Requires-Dist: typing-extensions (>=4.12.2,<5.0.0)
Project-URL: Documentation, https://pages.nist.gov/etspy/
Project-URL: Repository, https://github.com/usnistgov/etspy/
